Cargo.toml
LICENSE
MANIFEST.in
README.rst
pyproject.toml
setup.py
fuzzy_json/__init__.py
fuzzy_json.egg-info/PKG-INFO
fuzzy_json.egg-info/SOURCES.txt
fuzzy_json.egg-info/dependency_links.txt
fuzzy_json.egg-info/not-zip-safe
fuzzy_json.egg-info/top_level.txt
src/lib.rs